aspose/__init__.py
aspose/cad.cpython-310-darwin.so
aspose/cad.cpython-311-darwin.so
aspose/cad.cpython-312-darwin.so
aspose/cad.cpython-38-darwin.so
aspose/cad.cpython-39-darwin.so
aspose/pycore.cpython-310-darwin.so
aspose/pycore.cpython-311-darwin.so
aspose/pycore.cpython-312-darwin.so
aspose/pycore.cpython-38-darwin.so
aspose/pycore.cpython-39-darwin.so
aspose/pydrawing.cpython-310-darwin.so
aspose/pydrawing.cpython-311-darwin.so
aspose/pydrawing.cpython-312-darwin.so
aspose/pydrawing.cpython-38-darwin.so
aspose/pydrawing.cpython-39-darwin.so
aspose/pygc.cpython-310-darwin.so
aspose/pygc.cpython-311-darwin.so
aspose/pygc.cpython-312-darwin.so
aspose/pygc.cpython-38-darwin.so
aspose/pygc.cpython-39-darwin.so
aspose/pyreflection.cpython-310-darwin.so
aspose/pyreflection.cpython-311-darwin.so
aspose/pyreflection.cpython-312-darwin.so
aspose/pyreflection.cpython-38-darwin.so
aspose/pyreflection.cpython-39-darwin.so
aspose/__pyinstaller/__init__.pyi
aspose/__pyinstaller/hook-aspose.py
aspose/assemblies/cad/Aspose.CAD.dll
aspose/assemblies/cad/MessagePack.Annotations.dll
aspose/assemblies/cad/MessagePack.dll
aspose/assemblies/cad/Microsoft.NET.StringTools.dll
aspose/assemblies/cad/System.Formats.Asn1.dll
aspose/assemblies/cad/System.Security.Cryptography.Pkcs.dll
aspose/assemblies/cad/System.Text.Encoding.CodePages.dll
aspose/assemblies/cad/WrpInterop.Aspose.CAD.dll
aspose/assemblies/cad/nuget.exe
aspose/assemblies/pycore/WrpInterop.Aspose.PyCore.dll
aspose/assemblies/pydrawing/Microsoft.Win32.SystemEvents.dll
aspose/assemblies/pydrawing/System.Drawing.Common.dll
aspose/assemblies/pydrawing/WrpInterop.Aspose.PyDrawing.dll
aspose/assemblies/pygc/Aspose.PyGC.dll
aspose/assemblies/pyreflection/WrpInterop.Aspose.PyReflection.dll
aspose/cad/__init__.pyi
aspose/cad/__nuitka/__init__.pyi
aspose/cad/__nuitka/aspose-cad.nuitka-package.config.yml
aspose/cad/__pyinstaller/__init__.pyi
aspose/cad/__pyinstaller/hook-aspose.cad.py
aspose/netcore/netcore6.0/Microsoft.CSharp.dll
aspose_cad-25.12.0.dist-info/METADATA
aspose_cad-25.12.0.dist-info/WHEEL
aspose_cad-25.12.0.dist-info/entry_points.txt
aspose_cad-25.12.0.dist-info/top_level.txt
aspose_cad-25.12.0.dist-info/RECORD
