Metadata-Version: 2.4
Name: aspose-cad
Version: 25.12.0
Summary: Aspose.CAD for Python is a CAD and BIM drawings Processing library that allows developers to modify, convert and publish various drawing and image formats without need to have any other CAD software.
Home-page: https://products.aspose.com/cad/python
Author: Aspose
License: https://company.aspose.com/legal/eula
Keywords: dwg,dwg to pdf,convert,publish,export,create,write,metadata,edit,modify,cad,bim,dxf,dgn,dwf,dwfx,ifc,stl,dxb,cf2,hpgl,plt,ply,ifc,iges,pcl,pdf-3d,dwt,dxb,3ds,u3d,stp,collada,obj,stp,jpg,png,j2k,psd,svg,pdf,wmf,dicom,webp,html5,gif
Platform: macos_arm64
Classifier: Intended Audience :: Developers
Classifier: Intended Audience :: Education
Classifier: License :: Other/Proprietary License
Classifier: License :: Free To Use But Restricted
Classifier: Operating System :: Microsoft :: Windows
Classifier: Operating System :: Unix
Classifier: Operating System :: MacOS
Classifier: Operating System :: MacOS :: MacOS X
Classifier: Operating System :: POSIX
Classifier: Programming Language :: Python :: 3
Classifier: Programming Language :: Python :: 3 :: Only
Classifier: Programming Language :: Python :: 3.5
Classifier: Programming Language :: Python :: 3.6
Classifier: Programming Language :: Python :: 3.7
Classifier: Programming Language :: Python :: 3.8
Classifier: Programming Language :: Python :: 3.9
Classifier: Programming Language :: Python :: 3.10
Classifier: Programming Language :: Python :: 3.11
Classifier: Programming Language :: Python :: 3.12
Classifier: Topic :: Software Development
Classifier: Topic :: Software Development :: Libraries
Classifier: Topic :: Office/Business
Requires-Python: >=3.5,<3.13
Dynamic: author
Dynamic: classifier
Dynamic: description
Dynamic: description-content-type
Dynamic: home-page
Dynamic: keywords
Dynamic: license
Dynamic: platform
Dynamic: requires-python
Dynamic: summary
